homo_his_heart_mcp-0.1.1.dist-info/licenses/LICENSE
time_server/__init__.py
time_server/time_server.py
homo_his_heart_mcp-0.1.1.dist-info/METADATA
homo_his_heart_mcp-0.1.1.dist-info/WHEEL
homo_his_heart_mcp-0.1.1.dist-info/top_level.txt
homo_his_heart_mcp-0.1.1.dist-info/RECORD
