Metadata-Version: 2.4
Name: homo-his-heart-mcp
Version: 0.1.1
Summary: A time server tool built with FastMCP
Author: Potatoes Ed Mash
Classifier: Programming Language :: Python :: 3
Classifier: License :: OSI Approved :: MIT License
Classifier: Operating System :: OS Independent
Requires-Python: >=3.8
License-File: LICENSE
Requires-Dist: pytz
Requires-Dist: fastmcp
Dynamic: license-file
